{
  "name": "Google Credentials",
  "nodes": [
    {
      "parameters": {
        "authentication": "oAuth2",
        "messageUi": {},
        "additionalFields": {}
      },
      "type": "n8n-nodes-base.googleChat",
      "typeVersion": 1,
      "position": [
        -32,
        -32
      ],
      "id": "eb84df07-f1ec-49a0-a9a9-e0412993bf17",
      "name": "Create a message",
      "webhookId": "d939b4ac-75cd-4118-b4c9-5a1935f38af3",
      "credentials": {
        "googleChatOAuth2Api": {
          "id": "Qa06qo8uZ2T1CfMq",
          "name": "Chat account"
        }
      }
    },
    {
      "parameters": {
        "pollTimes": {
          "item": [
            {
              "mode": "everyMinute"
            }
          ]
        },
        "triggerOn": "specificFile",
        "fileToWatch": {
          "__rl": true,
          "mode": "list",
          "value": ""
        }
      },
      "type": "n8n-nodes-base.googleDriveTrigger",
      "typeVersion": 1,
      "position": [
        176,
        -32
      ],
      "id": "d02cee70-98da-45d1-971a-198b56e03d3d",
      "name": "Google Drive Trigger",
      "credentials": {
        "googleDriveOAuth2Api": {
          "id": "tR6LC31n7HlHd5zt",
          "name": "Google Drive account"
        }
      }
    }
  ],
  "pinData": {},
  "connections": {},
  "active": false,
  "settings": {
    "executionOrder": "v1"
  },
  "versionId": "c609575e-1bec-49a9-b33c-6d1c09ea814a",
  "meta": {
    "templateCredsSetupCompleted": true,
    "instanceId": "7a3f4b30d139bb4d4da62ccf6bec8aefe503a6057c743693063b0411d7afe9d0"
  },
  "id": "84PiL67k6u5dzfZP",
  "tags": []
}